MANIFEST.in
README.md
setup.py
geofinder_vt/ImageExtractor.py
geofinder_vt/VideoConverter.py
geofinder_vt/__init__.py
geofinder_vt/gpmf_support.py
geofinder_vt/vid_extract.py
geotesting_vt.egg-info/PKG-INFO
geotesting_vt.egg-info/SOURCES.txt
geotesting_vt.egg-info/dependency_links.txt
geotesting_vt.egg-info/requires.txt
geotesting_vt.egg-info/top_level.txt