Metadata-Version: 2.1
Name: geotesting-vt
Version: 0.2.13
Summary: A brief description of your package
Home-page: https://github.com/nathan846/geofindervt
Author: Your Name
Author-email: vaidhyanathan@vt.edu
License: UNKNOWN
Platform: UNKNOWN
Classifier: Programming Language :: Python :: 3
Classifier: License :: OSI Approved :: MIT License
Classifier: Operating System :: OS Independent
